test_z/__init__.py
test_z/__main__.py
test_z-0.1.1.dist-info/METADATA
test_z-0.1.1.dist-info/WHEEL
test_z-0.1.1.dist-info/top_level.txt
test_z-0.1.1.dist-info/RECORD
